wherepy.py
wherepy-1.2.0.dist-info/LICENSE
wherepy-1.2.0.dist-info/METADATA
wherepy-1.2.0.dist-info/WHEEL
wherepy-1.2.0.dist-info/RECORD
